{
  "type": "Script",
  "directives": [],
  "statements": [
    {
      "type": "VariableDeclarationStatement",
      "declaration": {
        "type": "VariableDeclaration",
        "kind": "const",
        "declarators": [
          {
            "type": "VariableDeclarator",
            "binding": {
              "type": "ObjectBinding",
              "properties": [
                {
                  "type": "BindingPropertyProperty",
                  "name": {
                    "type": "StaticPropertyName",
                    "value": "a",
                    "loc": {
                      "start": {
                        "line": 1,
                        "column": 7,
                        "offset": 7
                      },
                      "end": {
                        "line": 1,
                        "column": 8,
                        "offset": 8
                      }
                    }
                  },
                  "binding": {
                    "type": "BindingIdentifier",
                    "name": "b",
                    "loc": {
                      "start": {
                        "line": 1,
                        "column": 9,
                        "offset": 9
                      },
                      "end": {
                        "line": 1,
                        "column": 10,
                        "offset": 10
                      }
                    }
                  },
                  "loc": {
                    "start": {
                      "line": 1,
                      "column": 7,
                      "offset": 7
                    },
                    "end": {
                      "line": 1,
                      "column": 10,
                      "offset": 10
                    }
                  }
                }
              ],
              "loc": {
                "start": {
                  "line": 1,
                  "column": 6,
                  "offset": 6
                },
                "end": {
                  "line": 1,
                  "column": 11,
                  "offset": 11
                }
              }
            },
            "init": {
              "type": "ObjectExpression",
              "properties": [],
              "loc": {
                "start": {
                  "line": 1,
                  "column": 14,
                  "offset": 14
                },
                "end": {
                  "line": 1,
                  "column": 16,
                  "offset": 16
                }
              }
            },
            "loc": {
              "start": {
                "line": 1,
                "column": 6,
                "offset": 6
              },
              "end": {
                "line": 1,
                "column": 16,
                "offset": 16
              }
            }
          }
        ],
        "loc": {
          "start": {
            "line": 1,
            "column": 0,
            "offset": 0
          },
          "end": {
            "line": 1,
            "column": 16,
            "offset": 16
          }
        }
      },
      "loc": {
        "start": {
          "line": 1,
          "column": 0,
          "offset": 0
        },
        "end": {
          "line": 1,
          "column": 16,
          "offset": 16
        }
      }
    }
  ],
  "loc": {
    "start": {
      "line": 1,
      "column": 0,
      "offset": 0
    },
    "end": {
      "line": 1,
      "column": 16,
      "offset": 16
    }
  }
}
